pydi_client/__init__.py
pydi_client/api/__init__.py
pydi_client/api/auth.py
pydi_client/api/collection.py
pydi_client/api/embedding_model.py
pydi_client/api/pipeline.py
pydi_client/api/schema.py
pydi_client/api/search.py
pydi_client/api/utils.py
pydi_client/data/__init__.py
pydi_client/data/collection_manager.py
pydi_client/data/model.py
pydi_client/data/pipeline.py
pydi_client/data/schema.py
pydi_client/di_client.py
pydi_client/errors.py
pydi_client/logger.py
pydi_client/sessions/__init__.py
pydi_client/sessions/authenticated_session.py
pydi_client/sessions/session.py
pydi_client-1.0.0.dist-info/LICENSE
pydi_client-1.0.0.dist-info/METADATA
pydi_client-1.0.0.dist-info/NOTICE.txt
pydi_client-1.0.0.dist-info/WHEEL
pydi_client-1.0.0.dist-info/RECORD
