Metadata-Version: 2.3
Name: pydi-client
Version: 1.0.0
Summary: Python client for data intelligence API
License: Apache-2.0
Author: HPE
Requires-Python: >=3.11.2
Classifier: License :: OSI Approved :: Apache Software License
Classifier: Programming Language :: Python :: 3
Classifier: Programming Language :: Python :: 3.12
Classifier: Programming Language :: Python :: 3.13
Requires-Dist: attrs (==23.1.0)
Requires-Dist: httpx (==0.27.0)
Requires-Dist: pydantic (==2.11.4)
Project-URL: Documentation, https://scod.hpedev.io/
Project-URL: Homepage, https://github.com/hpe-storage/pydi-client
Project-URL: Repository, https://github.com/hpe-storage/pydi-client
